{
  "Post": {
    "title": { "string": {} },
    "body": { "string": {} },
    "userId": {
      "hasMany": "Comment"
    }
  },
  "User": {
    "name": { "string": [
      "Leanne",
      "Stacy",
      "Liam"
    ]},
    "username": { "regexp": "[A-Z][a-z]{5,10}" },
    "email": { "regexp": "[a-z]{5,10}@[a-z]{5}\\.[a-z]{2,3}" },
    "address": {
      "street": { "regexp": "[A-Z][a-z]{5,10}" },
      "suite": { "regexp": "[A-Z][a-z]{5,10}" },
      "city": { "regexp": "[A-Z][a-z]{5,10}" },
      "zipcode": { "int": { "min": 0, "max": 400 } },
      "geo": {
        "lat": { "int": { "min": -100, "max": 0 } },
        "lng": { "int": { "min": 0, "max": 100 } }
        }
      },
    "phone": { "int": { "min": 0, "max": 400000 } },
    "website": { "regexp": "[a-z]{5}\\.[a-z]{2,3}" },
    "company": {
      "name": { "regexp": "[A-Z][a-z]{5,10}" },
      "catchPhrase": { "regexp": "[A-Z][a-z]{5,10}" },
      "bs": { "regexp": "[A-Z][a-z]{5,10}" },
      },
    "post": {
      "belongsTo": "Post"
    }
  },
  "Extapistat": {
    "name": { "string": [
      "restcountries",
      "timezonedb",
      "countries-now",
      "aviation-stack-cities",
      "fixer-io"
    ]},
    "status": { "string": [
      "STARTED",
      "IN PROGRESS",
      "COMPLETED",
      "ERROR",
      "CANCELLED"
    ]},
    "item_count": { "int": { "min": 0, "max": 400 } },
    "start_time": { "dateTime": {
      "min": "2010-01-01T00:00:00Z",
      "max": "2020-12-31T23:59:59Z"
    }},
    "finish_time": { "dateTime": {
      "min": "2010-01-01T00:00:00Z",
      "max": "2020-12-31T23:59:59Z"
    }},
    "elapsed_time": { "int": { "min": 0, "max": 400 } }
  }
}
